smude/__init__.py
smude/binarize.py
smude/cli.py
smude/model.py
smude/mrcdi.py
smude/roi.py
smude/utils.py
smude-0.2.1.dist-info/METADATA
smude-0.2.1.dist-info/WHEEL
smude-0.2.1.dist-info/entry_points.txt
smude-0.2.1.dist-info/licenses/LICENSE.md
smude-0.2.1.dist-info/RECORD
