Metadata-Version: 2.4
Name: smude
Version: 0.2.1
Summary: Sheet Music Dewarping - Binarization and rectification of sheet music images
Project-URL: Homepage, https://github.com/sonovice/smude
Project-URL: Repository, https://github.com/sonovice/smude
Project-URL: Issues, https://github.com/sonovice/smude/issues
Author: Simon Waloschek
License-Expression: LicenseRef-Commons-Clause-AGPL-3.0
License-File: LICENSE.md
Keywords: binarization,dewarping,image processing,music,ocr,sheet music
Classifier: Development Status :: 4 - Beta
Classifier: Intended Audience :: Developers
Classifier: Intended Audience :: Science/Research
Classifier: Programming Language :: Python :: 3
Classifier: Programming Language :: Python :: 3.10
Classifier: Programming Language :: Python :: 3.11
Classifier: Programming Language :: Python :: 3.12
Classifier: Programming Language :: Python :: 3.13
Classifier: Topic :: Multimedia :: Graphics :: Graphics Conversion
Classifier: Topic :: Scientific/Engineering :: Image Processing
Requires-Python: >=3.10
Requires-Dist: numpy>=1.24.0
Requires-Dist: opencv-contrib-python>=4.7.0
Requires-Dist: pytorch-lightning>=2.0.0
Requires-Dist: requests>=2.28.0
Requires-Dist: scikit-image>=0.21.0
Requires-Dist: scipy>=1.10.0
Requires-Dist: torch>=2.0.0
Requires-Dist: torchvision>=0.15.0
Requires-Dist: tqdm>=4.65.0
Requires-Dist: typing-extensions>=4.5.0
